qgis_plugin_tools/__init__.py
qgis_plugin_tools/py.typed
qgis_plugin_tools/infrastructure/__init__.py
qgis_plugin_tools/infrastructure/debugging.py
qgis_plugin_tools/infrastructure/plugin_maker.py
qgis_plugin_tools/resources/ui/progress_dialog.ui
qgis_plugin_tools/testing/__init__.py
qgis_plugin_tools/testing/utilities.py
qgis_plugin_tools/tools/__init__.py
qgis_plugin_tools/tools/algorithm_processing.py
qgis_plugin_tools/tools/custom_logging.py
qgis_plugin_tools/tools/decorations.py
qgis_plugin_tools/tools/exceptions.py
qgis_plugin_tools/tools/fields.py
qgis_plugin_tools/tools/ghost_layers.py
qgis_plugin_tools/tools/i18n.py
qgis_plugin_tools/tools/layers.py
qgis_plugin_tools/tools/logger_processing.py
qgis_plugin_tools/tools/messages.py
qgis_plugin_tools/tools/misc_utils.py
qgis_plugin_tools/tools/network.py
qgis_plugin_tools/tools/raster_layers.py
qgis_plugin_tools/tools/resources.py
qgis_plugin_tools/tools/settings.py
qgis_plugin_tools/tools/tasks.py
qgis_plugin_tools/tools/ui.py
qgis_plugin_tools/tools/version.py
qgis_plugin_tools/widgets/__init__.py
qgis_plugin_tools/widgets/grid_layout_utils.py
qgis_plugin_tools/widgets/json_editor.py
qgis_plugin_tools/widgets/list_fields_selection.py
qgis_plugin_tools/widgets/list_layers_selection.py
qgis_plugin_tools/widgets/progress_dialog.py
qgis_plugin_tools/widgets/selectable_combobox.py
qgis_plugin_tools-0.5.0.dist-info/LICENSE
qgis_plugin_tools-0.5.0.dist-info/METADATA
qgis_plugin_tools-0.5.0.dist-info/WHEEL
qgis_plugin_tools-0.5.0.dist-info/top_level.txt
qgis_plugin_tools-0.5.0.dist-info/RECORD
