Metadata-Version: 2.1
Name: qgis_plugin_tools
Version: 0.5.0
Summary: A collection of helpful tools and widgets to aid QGIS plugin tool development
Home-page: https://github.com/GispoCoding/qgis_plugin_tools
Author: 3Liz, Gispo Ltd.
Author-email: info@gispo.fi
Maintainer: Gispo Ltd.
Maintainer-email: info@gispo.fi
License: GNU GPL v2.0
Keywords: qgis,QGIS,PyQGIS
Classifier: Development Status :: 4 - Beta
Classifier: Intended Audience :: Developers
Classifier: Topic :: Software Development :: Libraries :: Python Modules
Classifier: Programming Language :: Python
Classifier: Programming Language :: Python :: 3
Classifier: Programming Language :: Python :: 3.5
Classifier: Programming Language :: Python :: 3.6
Classifier: Programming Language :: Python :: 3.7
Classifier: Programming Language :: Python :: 3.8
Classifier: Programming Language :: Python :: 3.9
Classifier: Programming Language :: Python :: 3.10
Classifier: Programming Language :: Python :: 3 :: Only
Classifier: Programming Language :: Python :: Implementation :: CPython
Classifier: Programming Language :: Python :: Implementation :: PyPy
Classifier: Operating System :: OS Independent
Classifier: License :: OSI Approved :: GNU General Public License v2 (GPLv2)
Requires-Python: >=3.5
License-File: LICENSE
